kard_x-0.1.2.dist-info/licenses/LICENSE
src/__init__.py
src/__main__.py
src/app_controller.py
src/card.py
src/game_state.py
src/keyboard.py
src/loader.py
src/player.py
src/settings.py
src/view_utils.py
src/data/__init__.py
src/data/cards.jsonc
src/data/characters.jsonc
src/data/settings.jsonc
src/scenes/__init__.py
src/scenes/character_select/__init__.py
src/scenes/character_select/character_select_controller.py
src/scenes/character_select/character_select_view.py
src/scenes/editor/card_editor_controller.py
src/scenes/editor/character_editor_controller.py
src/scenes/editor/editor_app_controller.py
src/scenes/editor/editor_menu_controller.py
src/scenes/editor/editor_menu_view.py
src/scenes/editor_menu/editor_menu_controller.py
src/scenes/editor_menu/editor_menu_view.py
src/scenes/game/__init__.py
src/scenes/game/game_controller.py
src/scenes/game/game_view.py
src/scenes/main_menu/__init__.py
src/scenes/main_menu/menu_controller.py
src/scenes/main_menu/menu_view.py
src/scenes/pause_menu/__init__.py
src/scenes/pause_menu/pause_menu_controller.py
src/scenes/pause_menu/pause_menu_view.py
src/scenes/settings/__init__.py
src/scenes/settings/settings_controller.py
src/scenes/settings/settings_view.py
kard_x-0.1.2.dist-info/METADATA
kard_x-0.1.2.dist-info/WHEEL
kard_x-0.1.2.dist-info/entry_points.txt
kard_x-0.1.2.dist-info/top_level.txt
kard_x-0.1.2.dist-info/RECORD
