Metadata-Version: 2.4
Name: kard-x
Version: 0.1.2
Summary: A fun, text-based card game built with Python and a customizable rule engine.
Author-email: Johnny <your.email@example.com>
License: MIT License
Project-URL: Homepage, https://github.com/JohnnyWu2k/kardx
Project-URL: Bug Tracker, https://github.com/JohnnyWu2k/kardx/issues
Classifier: Development Status :: 3 - Alpha
Classifier: Environment :: Console
Classifier: Intended Audience :: End Users/Desktop
Classifier: License :: OSI Approved :: MIT License
Classifier: Operating System :: OS Independent
Classifier: Programming Language :: Python :: 3
Classifier: Topic :: Games/Entertainment :: Board Games
Requires-Python: >=3.10
License-File: LICENSE
Requires-Dist: json5
Requires-Dist: wcwidth
Dynamic: license-file
